eng_to_ru/__init__.py
eng_to_ru/eng_to_ru.py
eng_to_ru-0.1.1.dist-info/METADATA
eng_to_ru-0.1.1.dist-info/WHEEL
eng_to_ru-0.1.1.dist-info/licenses/LICENSE
eng_to_ru-0.1.1.dist-info/RECORD
