Metadata-Version: 2.4
Name: eng_to_ru
Version: 0.1.1
Summary: Библиотека для перевода текста с английского на русский с использованием Google Translate API.
Project-URL: Homepage, https://github.com/rrfedorovich/eng_to_ru
Author-email: rrfedorovich <rrfedorovich@gmail.com>
License-File: LICENSE
Classifier: License :: OSI Approved :: MIT License
Classifier: Operating System :: OS Independent
Classifier: Programming Language :: Python :: 3
Requires-Python: >=3.8
Requires-Dist: deep-translator>=1.11.4
